mcp_linear_app/__init__.py
mcp_linear_app/server.py
mcp_linear_app-0.0.2.dist-info/METADATA
mcp_linear_app-0.0.2.dist-info/WHEEL
mcp_linear_app-0.0.2.dist-info/entry_points.txt
mcp_linear_app-0.0.2.dist-info/top_level.txt
mcp_linear_app-0.0.2.dist-info/RECORD
